contrastive_vi/__init__.py
contrastive_vi/data/__init__.py
contrastive_vi/data/utils.py
contrastive_vi/data/dataloaders/__init__.py
contrastive_vi/data/dataloaders/contrastive_dataloader.py
contrastive_vi/data/dataloaders/data_splitting.py
contrastive_vi/data/datasets/__init__.py
contrastive_vi/data/datasets/haber_2017.py
contrastive_vi/data/datasets/mcfarland_2020.py
contrastive_vi/data/datasets/norman_2019.py
contrastive_vi/data/datasets/papalexi_2021.py
contrastive_vi/data/datasets/zheng_2017.py
contrastive_vi/model/__init__.py
contrastive_vi/model/contrastive_vi.py
contrastive_vi/model/total_contrastive_vi.py
contrastive_vi/model/base/__init__.py
contrastive_vi/model/base/training_mixin.py
contrastive_vi/module/__init__.py
contrastive_vi/module/contrastive_vi.py
contrastive_vi/module/total_contrastive_vi.py
contrastive_vi/module/utils.py
tests/__init__.py
tests/utils.py
tests/model/__init__.py
tests/model/test_contrastive_vi.py
tests/module/__init__.py
tests/module/test_contrastive_vi.py
contrastive_vi-0.2.0.dist-info/LICENSE
contrastive_vi-0.2.0.dist-info/METADATA
contrastive_vi-0.2.0.dist-info/WHEEL
contrastive_vi-0.2.0.dist-info/top_level.txt
contrastive_vi-0.2.0.dist-info/RECORD
