Metadata-Version: 2.1
Name: contrastive-vi
Version: 0.2.0
Requires-Python: >=3.7
License-File: LICENSE
Requires-Dist: scanpy (>=1.8.1)
Requires-Dist: protobuf (<=3.20.1)
Requires-Dist: scvi-tools (==0.16.1)
Provides-Extra: dev
Requires-Dist: pre-commit (==2.15.0) ; extra == 'dev'
Requires-Dist: toml (==0.10.2) ; extra == 'dev'
Requires-Dist: pytest (==6.2.5) ; extra == 'dev'
